{
  "generated_at": "2026-06-14T09:04:39Z",
  "niches_processed": [
    "foot wellness",
    "posture corrector",
    "sleep supplement",
    "hair loss",
    "joint pain",
    "weight loss",
    "gut health",
    "collagen",
    "anti aging",
    "teeth whitening"
  ],
  "total_ads": 0,
  "results": [
    {
      "niche": "foot wellness",
      "angle_kpis": [],
      "gaps": [],
      "advertisers": [
        {
          "name": "vls-wellness.myshopify.com",
          "domain": "vls-wellness.myshopify.com",
          "store_url": "https://vls-wellness.myshopify.com",
          "scaling_score": 78.5,
          "ads_count": 0,
          "max_days_running": 0,
          "avg_days_running": 0.0,
          "estimated_spend": 0,
          "angles_used": [],
          "dominant_angle": "",
          "angle_gaps": [],
          "products": [
            {
              "title": "Full Back and Neck Massager",
              "vendor": "VLS Wellness",
              "product_type": "Heathcare",
              "tags": [],
              "price": "12999.0",
              "price_max": "",
              "compare_at_price": "21999.0",
              "discount_pct": 41,
              "available": false,
              "in_stock_variants": 0,
              "variants_count": 1,
              "options": [],
              "images_count": 5,
              "image": "https://cdn.shopify.com/s/files/1/0737/4585/8638/files/43253564646.webp?v=1780909430",
              "url": "https://vls-wellness.myshopify.com/products/full-back-and-neck-massager",
              "published_days": 5,
              "description": "Full Back and Neck Massager by VLS Wellness – Ultimate Relaxation &amp; Pain Relief Solution Experience complete relaxation and comfort with the Full Back and Neck Massager by VLS Wellness . Specially designed for modern lifestyles, this advanced massager helps relieve stress, reduce muscle tension, and improve blood circulation—all from the comfort of your home, office, or car. Whether you're dea"
            },
            {
              "title": "VLS Back Massager Cushion – Deep Kneading Shiatsu Massage with Heat Therapy",
              "vendor": "VLS Wellness",
              "product_type": "Personal care Product",
              "tags": [],
              "price": "5999.0",
              "price_max": "",
              "compare_at_price": "11999.0",
              "discount_pct": 50,
              "available": false,
              "in_stock_variants": 0,
              "variants_count": 1,
              "options": [],
              "images_count": 5,
              "image": "https://cdn.shopify.com/s/files/1/0737/4585/8638/files/massages-07.webp?v=1780313882",
              "url": "https://vls-wellness.myshopify.com/products/vls-back-massager-cushion-deep-kneading-shiatsu-massage-with-heat-therapy",
              "published_days": 16,
              "description": "Deep Tissue Pain Relief – The 12 kneading massage balls work deeply into muscles to relieve back, neck &amp; shoulder pain effectively. Reduces Stress &amp; Fatigue – Helps relax your body and mind after long working hours, reducing daily stress and tiredness. Improves Blood Circulation – Continuous kneading action boosts circulation, promoting better oxygen flow and faster recovery. Relieves Musc"
            },
            {
              "title": "VLS Premium Ergonomic Contoured Backrest – Firm Density Lumbar Support with Breathable Mesh for All-Day Comfort (Office & Car)",
              "vendor": "VLS Wellness",
              "product_type": "",
              "tags": [],
              "price": "999.0",
              "price_max": "",
              "compare_at_price": "1799.0",
              "discount_pct": 44,
              "available": false,
              "in_stock_variants": 0,
              "variants_count": 1,
              "options": [],
              "images_count": 5,
              "image": "https://cdn.shopify.com/s/files/1/0737/4585/8638/files/massage-07.webp?v=1780315969",
              "url": "https://vls-wellness.myshopify.com/products/vls-premium-ergonomic-contoured-backrest-firm-density-lumbar-support-with-breathable-mesh-for-all-day-comfort-office-car",
              "published_days": 17,
              "description": "VLS WELLNESS Full Backrest - Long sitting ka perfect solution Product Description Upgrade your sitting comfort with the VLS WELLNESS Full Backrest, designed to provide proper spinal support and long-lasting comfort during extended sitting hours. Whether you’re working, driving, or relaxing at home, this ergonomically designed backrest supports your neck, upper back, lower back, and lumbar region, "
            },
            {
              "title": "VLS Lower Backrest – Firm Foam Support with Breathable Mesh",
              "vendor": "VLS Wellness",
              "product_type": "",
              "tags": [],
              "price": "599.0",
              "price_max": "",
              "compare_at_price": "1199.0",
              "discount_pct": 50,
              "available": false,
              "in_stock_variants": 0,
              "variants_count": 1,
              "options": [],
              "images_count": 6,
              "image": "https://cdn.shopify.com/s/files/1/0737/4585/8638/files/massages-09.webp?v=1780314353",
              "url": "https://vls-wellness.myshopify.com/products/vls-lower-backrest-firm-foam-support-with-breathable-mesh",
              "published_days": 17,
              "description": "VLS WELLNESS Mini Backrest (Lumbar Support Cushion) - “Chhota Cushion, Bada Comfort ! Sit better, feel better\" Product Description Introducing the VLS WELLNESS Mini Backrest, specially designed to provide targeted lumbar support and improve your sitting posture. Its compact, curved design fits perfectly in the lower back (lumbar region), filling the gap between your spine and the chair—helping you"
            },
            {
              "title": "VLS Cervical Pillow – Premium Memory Foam with Ergonomic Contour Design",
              "vendor": "VLS Wellness",
              "product_type": "",
              "tags": [],
              "price": "899.0",
              "price_max": "",
              "compare_at_price": "1599.0",
              "discount_pct": 44,
              "available": false,
              "in_stock_variants": 0,
              "variants_count": 1,
              "options": [],
              "images_count": 5,
              "image": "https://cdn.shopify.com/s/files/1/0737/4585/8638/files/massages-08.png?v=1780314167",
              "url": "https://vls-wellness.myshopify.com/products/vls-cervical-pillow-premium-memory-foam-with-ergonomic-contour-design",
              "published_days": 17,
              "description": "Product Description Experience proper neck support and deeper sleep with the VLS WELLNESS Cervical Pillow. Designed with an ergonomic contoured shape, this pillow gently supports your neck and shoulders, helping maintain the natural curve of your spine while you sleep. It adapts to your sleeping position—whether you sleep on your back or side—reducing stiffness, discomfort, and morning neck pain. "
            },
            {
              "title": "VLS Ortho Coccyx Cushion – High density Memory Foam Support with U-Shape Design",
              "vendor": "VLS Wellness",
              "product_type": "",
              "tags": [],
              "price": "1099.0",
              "price_max": "",
              "compare_at_price": "1799.0",
              "discount_pct": 39,
              "available": false,
              "in_stock_variants": 0,
              "variants_count": 1,
              "options": [],
              "images_count": 6,
              "image": "https://cdn.shopify.com/s/files/1/0737/4585/8638/files/massage-09.png?v=1780314577",
              "url": "https://vls-wellness.myshopify.com/products/vls-ortho-coccyx-cushion-high-density-memory-foam-support-with-u-shape-design",
              "published_days": 17,
              "description": "VLS WELLNESS Coccyx Support Cushion (Tailbone Relief Seat) Comfort That Supports You All Day Product Description Sit comfortably for longer hours with the VLS WELLNESS Coccyx Support Cushion, designed to relieve pressure from the tailbone (coccyx). Its U-shaped cut-out design suspends the tailbone in air, reducing direct pressure and helping ease discomfort caused by long sitting, driving, or post"
            },
            {
              "title": "Advanced Foot,Calves,knee,and Arm Massager For Relaxation",
              "vendor": "VLS Wellness",
              "product_type": "",
              "tags": [],
              "price": "6499.0",
              "price_max": "",
              "compare_at_price": "11999.0",
              "discount_pct": 46,
              "available": false,
              "in_stock_variants": 0,
              "variants_count": 1,
              "options": [],
              "images_count": 5,
              "image": "https://cdn.shopify.com/s/files/1/0737/4585/8638/files/foot-2.webp?v=1780296570",
              "url": "https://vls-wellness.myshopify.com/products/advanced-foot-calves-knee-and-arm-massager-for-relaxation",
              "published_days": 17,
              "description": "FOOT MASSAGER by VLS Wellness – Advanced Relaxation for Your Feet The FOOT MASSAGER by VLS Wellness is designed to provide deep relaxation, improved circulation, and ultimate comfort for tired feet. After a long day of standing, walking, or working, your feet deserve professional care. This advanced FOOT MASSAGER delivers a soothing massage experience that helps relieve fatigue, reduce stress, and"
            },
            {
              "title": "Prime Relief Robotic 4D Massager – Detachable Multi-Use Leg",
              "vendor": "VLS Wellness",
              "product_type": "",
              "tags": [],
              "price": "27999.0",
              "price_max": "",
              "compare_at_price": "49900.0",
              "discount_pct": 44,
              "available": false,
              "in_stock_variants": 0,
              "variants_count": 1,
              "options": [],
              "images_count": 6,
              "image": "https://cdn.shopify.com/s/files/1/0737/4585/8638/files/wr3tet5.webp?v=1780910355",
              "url": "https://vls-wellness.myshopify.com/products/prime-relief-robotic-4d-massager-detachable-multi-use-leg",
              "published_days": 17,
              "description": "Robotic 4D Massager – Premium Description Experience advanced relaxation with the VLS LF32 Robotic 4D Massager, designed to deliver deep, effective relief for your legs, knees, thighs, calves, feet, and even arms. Advanced Acupressure &amp; 4D Massage Specially designed kneading panels target key pressure points across your thighs and legs, inspired by professional massage techniques for deeper re"
            },
            {
              "title": "Premium Brown Body Relaxation Massager For Home and Office Use",
              "vendor": "VLS Wellness",
              "product_type": "",
              "tags": [],
              "price": "89999.0",
              "price_max": "",
              "compare_at_price": "199000.0",
              "discount_pct": 55,
              "available": false,
              "in_stock_variants": 0,
              "variants_count": 1,
              "options": [],
              "images_count": 6,
              "image": "https://cdn.shopify.com/s/files/1/0737/4585/8638/files/massage-01.webp?v=1780309008",
              "url": "https://vls-wellness.myshopify.com/products/premium-brown-body-relaxation-massager-for-home-and-office-use",
              "published_days": 17,
              "description": "Body Relaxation Massager For Home and Office Use: VLS Wellness LC02 In the hustle and bustle of modern life, stress, fatigue, and muscle tension are inevitable. Whether you are working long hours at the office or managing household responsibilities, your body deserves premium care. Enter the VLS LC02 Body Relaxation Massager for home and office use – a cutting-edge massage chair designed to transf"
            },
            {
              "title": "VLS Snake Travel Pillow – Wrap Yourself in Comfort",
              "vendor": "VLS Wellness",
              "product_type": "",
              "tags": [],
              "price": "1199.0",
              "price_max": "",
              "compare_at_price": "1899.0",
              "discount_pct": 37,
              "available": false,
              "in_stock_variants": 0,
              "variants_count": 1,
              "options": [],
              "images_count": 5,
              "image": "https://cdn.shopify.com/s/files/1/0737/4585/8638/files/massage-06.webp?v=1780316461",
              "url": "https://vls-wellness.myshopify.com/products/vls-snake-travel-pillow-wrap-yourself-in-comfort",
              "published_days": 17,
              "description": "VLS Snake Travel Pillow – Wrap Yourself in Comfort Concept Unlike ordinary U-shaped pillows, the VLS Snake Pillow is designed to wrap around your neck like a snake, giving you secure, flexible, and complete support from every angle. Why Snake Shape Matters Most travel pillows leave gaps this one doesn’t. 360° Wrap-Around Support The snake-inspired design coils gently around your neck, supporting b"
            },
            {
              "title": "4D Advanced Foot Calf & Thigh Massager – Air Compression + Roller Therapy with Heat",
              "vendor": "VLS Wellness",
              "product_type": "",
              "tags": [],
              "price": "34999.0",
              "price_max": "",
              "compare_at_price": "53999.0",
              "discount_pct": 35,
              "available": false,
              "in_stock_variants": 0,
              "variants_count": 1,
              "options": [],
              "images_count": 7,
              "image": "https://cdn.shopify.com/s/files/1/0737/4585/8638/files/foot-1.webp?v=1780293579",
              "url": "https://vls-wellness.myshopify.com/products/4d-advanced-foot-calf-thigh-massager-air-compression-roller-therapy-with-heat",
              "published_days": 18,
              "description": "4D Advanced Foot Calf &amp; Thigh Massager – Air Compression + Roller Therapy with Heat VLS LF06 Neo – 4D Advanced Leg &amp; Foot Massager Experience Deep Relaxation Like Never Before Dual Action Foot Rollers with Scrubbing Powerful rollers combined with a gentle scrubbing effect to target pressure points and relieve deep foot fatigue. Movable Calf Rollers Technology Dynamic rollers glide smoothly"
            },
            {
              "title": "4D Ultra Premium Top End Luxury Massage Chair",
              "vendor": "VLS Wellness",
              "product_type": "",
              "tags": [],
              "price": "399000.0",
              "price_max": "",
              "compare_at_price": "599000.0",
              "discount_pct": 33,
              "available": false,
              "in_stock_variants": 0,
              "variants_count": 1,
              "options": [],
              "images_count": 6,
              "image": "https://cdn.shopify.com/s/files/1/0737/4585/8638/files/massages-03.webp?v=1780311401",
              "url": "https://vls-wellness.myshopify.com/products/4d-ultra-premium-top-end-luxury-massage-chair",
              "published_days": 18,
              "description": "4D Ultra Premium Top End Luxury Massage Chair – Smart Wellness Redefined by VLS Wellness Experience next-level relaxation with the 4D Ultra Premium Top End Luxury Massage Chair from VLS Wellness . Designed with intelligent features, modern controls, and advanced 4D technology, this premium massage chair offers a spa-like experience at home. Whether you want stress relief, muscle recovery, or daily"
            },
            {
              "title": "4D Full Body Luxury Smart Massage Chair – Zero Gravity Multifunctional Body Care System",
              "vendor": "VLS Wellness",
              "product_type": "",
              "tags": [],
              "price": "329999.0",
              "price_max": "",
              "compare_at_price": "499900.0",
              "discount_pct": 34,
              "available": false,
              "in_stock_variants": 0,
              "variants_count": 1,
              "options": [],
              "images_count": 8,
              "image": "https://cdn.shopify.com/s/files/1/0737/4585/8638/files/massages-02.webp?v=1780311228",
              "url": "https://vls-wellness.myshopify.com/products/4d-full-body-luxury-smart-massage-chair-zero-gravity-multifunctional-body-care-system",
              "published_days": 18,
              "description": "4D Full Body Luxury Smart Massage Chair Experience ultimate relaxation and therapeutic comfort with the 4D Full Body Luxury Smart Massage Chair by VLS Wellness . Engineered with cutting-edge 4D massage technology, this premium massage chair is designed to provide a full-body massage experience that mimics the skilled hands of a professional therapist. Whether you’re seeking relief from chronic bac"
            },
            {
              "title": "Luxury Massage Chair 4D by VLS Wellness",
              "vendor": "VLS Wellness",
              "product_type": "",
              "tags": [],
              "price": "269000.0",
              "price_max": "",
              "compare_at_price": "399999.0",
              "discount_pct": 33,
              "available": false,
              "in_stock_variants": 0,
              "variants_count": 1,
              "options": [],
              "images_count": 5,
              "image": "https://cdn.shopify.com/s/files/1/0737/4585/8638/files/massage-5.webp?v=1780307714",
              "url": "https://vls-wellness.myshopify.com/products/luxury-massage-chair-4d-by-vls-wellness",
              "published_days": 18,
              "description": "Luxury Massage Chair 4D by VLS Wellness Indulge in the pinnacle of comfort and relaxation with the Luxury Massage Chair 4D from VLS Wellness . Engineered to deliver an unparalleled massage experience, this chair combines state-of-the-art technology with premium design to transform your home into a personal wellness sanctuary. Advanced 4D Massage Technology The Luxury Massage Chair 4D features cutt"
            },
            {
              "title": "VLS Wellness Extended Handle Deep Tissue Massage Gun With powerful speeds",
              "vendor": "VLS Wellness",
              "product_type": "",
              "tags": [],
              "price": "2199.0",
              "price_max": "",
              "compare_at_price": "3799.0",
              "discount_pct": 42,
              "available": false,
              "in_stock_variants": 0,
              "variants_count": 1,
              "options": [],
              "images_count": 6,
              "image": "https://cdn.shopify.com/s/files/1/0737/4585/8638/files/gun-02.webp?v=1780310670",
              "url": "https://vls-wellness.myshopify.com/products/vls-wellness-extended-handle-deep-tissue-massage-gun-with-powerful-speeds",
              "published_days": 18,
              "description": "VLS Wellness Extended Handle Deep Tissue Massage Gun Discover the ultimate solution for muscle relief and recovery with the Extended Handle Deep Tissue Massage Gun by VLS Wellness . Engineered to deliver professional-grade percussive therapy in the comfort of your home, this advanced massage gun combines ergonomics, power, and versatility to address every muscle tension, knot, and pain point effic"
            }
          ],
          "ad_examples": [],
          "platforms": [],
          "revenue_estimate": {
            "monthly_spend_est": 6000,
            "monthly_revenue_est": 21000,
            "confidence": "medium"
          },
          "landing_analysis": null,
          "scaling_signals": [],
          "collections_count": 7,
          "avg_product_price": 78899.13,
          "products_with_discount": 15,
          "products_with_reviews": 0,
          "avg_product_rating": null,
          "velocity": {
            "data_points": 0,
            "new_products": [],
            "removed_products": [],
            "price_changes": [],
            "signals": [],
            "launch_score": 0
          }
        },
        {
          "name": "fresh-healthy-3.myshopify.com",
          "domain": "fresh-healthy-3.myshopify.com",
          "store_url": "https://fresh-healthy-3.myshopify.com",
          "scaling_score": 16.0,
          "ads_count": 0,
          "max_days_running": 0,
          "avg_days_running": 0.0,
          "estimated_spend": 0,
          "angles_used": [],
          "dominant_angle": "",
          "angle_gaps": [],
          "products": [
            {
              "title": "ELECTRONIC VENDOR",
              "vendor": "VAULTSELLS",
              "product_type": "",
              "tags": [],
              "price": "20.0",
              "price_max": "",
              "compare_at_price": "",
              "discount_pct": 0,
              "available": true,
              "in_stock_variants": 1,
              "variants_count": 1,
              "options": [],
              "images_count": 1,
              "image": "https://cdn.shopify.com/s/files/1/0997/3504/4467/files/Screenshot2026-06-07135346.png?v=1780855237",
              "url": "https://fresh-healthy-3.myshopify.com/products/electronic-vendor",
              "published_days": 6,
              "description": "The wholesale tech plug. iPhones, AirPods, Apple Watch at prices that make the margins insane. Easy flips, fast money."
            },
            {
              "title": "COLOGNE VENDOR",
              "vendor": "VAULTSELLS",
              "product_type": "",
              "tags": [],
              "price": "30.0",
              "price_max": "",
              "compare_at_price": "",
              "discount_pct": 0,
              "available": true,
              "in_stock_variants": 1,
              "variants_count": 1,
              "options": [],
              "images_count": 1,
              "image": "https://cdn.shopify.com/s/files/1/0997/3504/4467/files/Screenshot2026-06-07135016.png?v=1780854638",
              "url": "https://fresh-healthy-3.myshopify.com/products/cologne-vendor",
              "published_days": 6,
              "description": "Designer fragrances at a fraction of retail. Tom Ford, Dior, JPG — clients can't tell the difference. Pure profit"
            },
            {
              "title": "CLOTHING VENDOR",
              "vendor": "VAULTSELLS",
              "product_type": "",
              "tags": [],
              "price": "20.0",
              "price_max": "",
              "compare_at_price": "",
              "discount_pct": 0,
              "available": true,
              "in_stock_variants": 1,
              "variants_count": 1,
              "options": [],
              "images_count": 1,
              "image": "https://cdn.shopify.com/s/files/1/0997/3504/4467/files/Screenshot2026-06-07132815.png?v=1780853406",
              "url": "https://fresh-healthy-3.myshopify.com/products/clothing-vendor",
              "published_days": 6,
              "description": "Access the same plug top resellers use for 1:1 streetwear. Sp5der, Hellstar, Chrome Hearts and more"
            }
          ],
          "ad_examples": [],
          "platforms": [],
          "revenue_estimate": {
            "monthly_spend_est": 1200,
            "monthly_revenue_est": 4200,
            "confidence": "low"
          },
          "landing_analysis": null,
          "scaling_signals": [],
          "collections_count": 2,
          "avg_product_price": 23.33,
          "products_with_discount": 0,
          "products_with_reviews": 0,
          "avg_product_rating": null,
          "velocity": {
            "data_points": 0,
            "new_products": [],
            "removed_products": [],
            "price_changes": [],
            "signals": [],
            "launch_score": 0
          }
        },
        {
          "name": "footrs.myshopify.com",
          "domain": "footrs.myshopify.com",
          "store_url": "https://footrs.myshopify.com",
          "scaling_score": 5.5,
          "ads_count": 0,
          "max_days_running": 0,
          "avg_days_running": 0.0,
          "estimated_spend": 0,
          "angles_used": [],
          "dominant_angle": "",
          "angle_gaps": [],
          "products": [
            {
              "title": "Lifetime Foot Relief Insoles",
              "vendor": "My Store",
              "product_type": "",
              "tags": [],
              "price": "43.0",
              "price_max": "",
              "compare_at_price": "44.0",
              "discount_pct": 2,
              "available": true,
              "in_stock_variants": 11,
              "variants_count": 11,
              "options": [
                "Shoe Size"
              ],
              "images_count": 7,
              "image": "https://cdn.shopify.com/s/files/1/1079/2075/2978/files/AI-Generated-Image-1_47.png?v=1780144293",
              "url": "https://footrs.myshopify.com/products/footrs-stepsole-pro",
              "published_days": 17,
              "description": "Step into all-day comfort with our premium plantar fasciitis relief insoles, designed to reduce foot pain, improve support, and keep you moving comfortably. Whether you're standing for long hours, walking daily, or dealing with heel pain, these insoles provide targeted cushioning and arch support where you need it most."
            }
          ],
          "ad_examples": [],
          "platforms": [],
          "revenue_estimate": {
            "monthly_spend_est": 1200,
            "monthly_revenue_est": 4200,
            "confidence": "low"
          },
          "landing_analysis": null,
          "scaling_signals": [],
          "collections_count": 1,
          "avg_product_price": 43.0,
          "products_with_discount": 1,
          "products_with_reviews": 0,
          "avg_product_rating": null,
          "velocity": {
            "data_points": 0,
            "new_products": [],
            "removed_products": [],
            "price_changes": [],
            "signals": [],
            "launch_score": 0
          }
        }
      ],
      "market_research": {},
      "market_revenue_est": 29400,
      "product_angle_matrix": [],
      "stats": {
        "total_ads": 0,
        "unique_angles": 0,
        "gaps_found": 0,
        "advertisers_found": 3
      }
    },
    {
      "niche": "posture corrector",
      "angle_kpis": [],
      "gaps": [],
      "advertisers": [],
      "market_research": {},
      "market_revenue_est": 0,
      "product_angle_matrix": [],
      "stats": {
        "total_ads": 0,
        "unique_angles": 0,
        "gaps_found": 0,
        "advertisers_found": 0
      }
    },
    {
      "niche": "sleep supplement",
      "angle_kpis": [],
      "gaps": [],
      "advertisers": [],
      "market_research": {},
      "market_revenue_est": 0,
      "product_angle_matrix": [],
      "stats": {
        "total_ads": 0,
        "unique_angles": 0,
        "gaps_found": 0,
        "advertisers_found": 0
      }
    },
    {
      "niche": "hair loss",
      "angle_kpis": [],
      "gaps": [],
      "advertisers": [],
      "market_research": {},
      "market_revenue_est": 0,
      "product_angle_matrix": [],
      "stats": {
        "total_ads": 0,
        "unique_angles": 0,
        "gaps_found": 0,
        "advertisers_found": 0
      }
    },
    {
      "niche": "joint pain",
      "angle_kpis": [],
      "gaps": [],
      "advertisers": [],
      "market_research": {},
      "market_revenue_est": 0,
      "product_angle_matrix": [],
      "stats": {
        "total_ads": 0,
        "unique_angles": 0,
        "gaps_found": 0,
        "advertisers_found": 0
      }
    },
    {
      "niche": "weight loss",
      "angle_kpis": [],
      "gaps": [],
      "advertisers": [],
      "market_research": {},
      "market_revenue_est": 0,
      "product_angle_matrix": [],
      "stats": {
        "total_ads": 0,
        "unique_angles": 0,
        "gaps_found": 0,
        "advertisers_found": 0
      }
    },
    {
      "niche": "gut health",
      "angle_kpis": [],
      "gaps": [],
      "advertisers": [],
      "market_research": {},
      "market_revenue_est": 0,
      "product_angle_matrix": [],
      "stats": {
        "total_ads": 0,
        "unique_angles": 0,
        "gaps_found": 0,
        "advertisers_found": 0
      }
    },
    {
      "niche": "collagen",
      "angle_kpis": [],
      "gaps": [],
      "advertisers": [],
      "market_research": {},
      "market_revenue_est": 0,
      "product_angle_matrix": [],
      "stats": {
        "total_ads": 0,
        "unique_angles": 0,
        "gaps_found": 0,
        "advertisers_found": 0
      }
    },
    {
      "niche": "anti aging",
      "angle_kpis": [],
      "gaps": [],
      "advertisers": [],
      "market_research": {},
      "market_revenue_est": 0,
      "product_angle_matrix": [],
      "stats": {
        "total_ads": 0,
        "unique_angles": 0,
        "gaps_found": 0,
        "advertisers_found": 0
      }
    },
    {
      "niche": "teeth whitening",
      "angle_kpis": [],
      "gaps": [],
      "advertisers": [],
      "market_research": {},
      "market_revenue_est": 0,
      "product_angle_matrix": [],
      "stats": {
        "total_ads": 0,
        "unique_angles": 0,
        "gaps_found": 0,
        "advertisers_found": 0
      }
    }
  ]
}